trytond/modules/health_ems/COPYING
trytond/modules/health_ems/README.rst
trytond/modules/health_ems/__init__.py
trytond/modules/health_ems/data/health_ems_sequence.xml
trytond/modules/health_ems/health_ems.py
trytond/modules/health_ems/health_ems_view.xml
trytond/modules/health_ems/icons/ambulance.svg
trytond/modules/health_ems/icons/operator.svg
trytond/modules/health_ems/locale/ar.po
trytond/modules/health_ems/locale/de.po
trytond/modules/health_ems/locale/el.po
trytond/modules/health_ems/locale/eo.po
trytond/modules/health_ems/locale/es.po
trytond/modules/health_ems/locale/fr.po
trytond/modules/health_ems/locale/health_ems.pot
trytond/modules/health_ems/locale/it_IT.po
trytond/modules/health_ems/locale/ja_JP.po
trytond/modules/health_ems/locale/ka.po
trytond/modules/health_ems/locale/lo.po
trytond/modules/health_ems/locale/pt_BR.po
trytond/modules/health_ems/locale/sv.po
trytond/modules/health_ems/locale/tr.po
trytond/modules/health_ems/locale/uk.po
trytond/modules/health_ems/locale/zh_CN.po
trytond/modules/health_ems/pyproject.toml
trytond/modules/health_ems/sequences.py
trytond/modules/health_ems/tests/__init__.py
trytond/modules/health_ems/tests/test_health_ems.py
trytond/modules/health_ems/tryton.cfg
trytond/modules/health_ems/view/ambulance_form.xml
trytond/modules/health_ems/view/ambulance_healthprofessional_form.xml
trytond/modules/health_ems/view/ambulance_healthprofessional_tree.xml
trytond/modules/health_ems/view/ambulance_support_form.xml
trytond/modules/health_ems/view/ambulance_support_tree.xml
trytond/modules/health_ems/view/ambulance_tree.xml
trytond/modules/health_ems/view/support_request_form.xml
trytond/modules/health_ems/view/support_request_log_form.xml
trytond/modules/health_ems/view/support_request_log_tree.xml
trytond/modules/health_ems/view/support_request_tree.xml
gnuhealth_ems-5.0.2.dist-info/METADATA
gnuhealth_ems-5.0.2.dist-info/WHEEL
gnuhealth_ems-5.0.2.dist-info/licenses/COPYING
gnuhealth_ems-5.0.2.dist-info/RECORD
